{"cameraMode":{"drawMode":0,"name":"Shaded","section":"Shading Mode"},"sceneLighting":true,"audioPlay":false,"sceneViewState":{"m_AlwaysRefresh":false,"showFog":true,"showSkybox":true,"showFlares":true,"showImageEffects":true,"showParticleSystems":true,"showVisualEffectGraphs":true,"m_FxEnabled":true},"in2DMode":false,"pivot":{"x":23.548555374145509,"y":6.571159839630127,"z":9.536918640136719},"rotation":{"x":0.06309753656387329,"y":0.7659536600112915,"z":-0.07607834786176682,"w":0.63526451587677},"size":7.5684709548950199,"orthographic":false}